easydarts/__init__.py
easydarts/calibration/__init__.py
easydarts/calibration/calibration.py
easydarts/cli/__init__.py
easydarts/cli/calibration.py
easydarts/cli/cli.py
easydarts/scorer/__init__.py
easydarts/scorer/scorer.py
easydarts-0.0.1.dist-info/LICENSE
easydarts-0.0.1.dist-info/METADATA
easydarts-0.0.1.dist-info/WHEEL
easydarts-0.0.1.dist-info/entry_points.txt
easydarts-0.0.1.dist-info/top_level.txt
easydarts-0.0.1.dist-info/RECORD
