Metadata-Version: 2.1
Name: easydarts
Version: 0.0.1
Summary: Steel darts calibration and score recognition system
Home-page: https://github.com/easydarts/easydarts
Author: Cidevant Von Goethe
Author-email: cidevant@mail.ru
License: MIT
Platform: UNKNOWN
Classifier: Programming Language :: Python
Classifier: Programming Language :: Python :: 3.6
Requires-Python: >=3.6
Requires-Dist: opencv-python
Requires-Dist: numpy
Requires-Dist: matplotlib
